pg-facile/__init__.py
pg-facile/database.py
pg_facile/__init__.py
pg_facile/database.py
pg_facile-0.0.5.dist-info/LICENSE
pg_facile-0.0.5.dist-info/METADATA
pg_facile-0.0.5.dist-info/WHEEL
pg_facile-0.0.5.dist-info/top_level.txt
pg_facile-0.0.5.dist-info/RECORD
