Metadata-Version: 2.1
Name: pg-facile
Version: 0.0.5
Summary: An easy-to-use wrapper for psycopg2 for students.
Home-page: https://github.com/pgrabolosa/pg-facile
Author: Pierre Grabolosa
Author-email: pierre.grabolosa@imerir.com
License: UNKNOWN
Platform: UNKNOWN
Classifier: Programming Language :: Python :: 3
Classifier: License :: OSI Approved :: MIT License
Classifier: Operating System :: OS Independent
Requires-Python: >=3.6
Requires-Dist: psycopg2-binary
